[{"name":"Qz8Y5uug","marks":13},{"name":"tl","marks":26},{"name":"Ze","marks":42},{"name":"heIasM","marks":64},{"name":"Ng3ItLUk","marks":57},{"name":"aeqnoMY","marks":15},{"name":"M","marks":19},{"name":"Pj","marks":46},{"name":"v","marks":9},{"name":"3Dd","marks":23},{"name":"0T3y3","marks":60},{"name":"2w","marks":13},{"name":"m19","marks":10},{"name":"CD2q","marks":19},{"name":"LJFVI5KyD8","marks":25},{"name":"xVHlVPSTZ4","marks":24},{"name":"ATo0CG","marks":73},{"name":"WhRHfcxN","marks":52},{"name":"bNnm","marks":11},{"name":"6FxlSfQ9jJ","marks":56},{"name":"eOO","marks":31},{"name":"jZ6y2ZIJtO","marks":13},{"name":"a","marks":85},{"name":"Gukoe8FA","marks":25},{"name":"DK6gdu8","marks":22},{"name":"Rneh","marks":93},{"name":"V58chVjN","marks":55},{"name":"h5o9","marks":85},{"name":"o6G7fNa1oh","marks":37},{"name":"ANu92","marks":14},{"name":"RAAoqgdC","marks":81},{"name":"avUHY8mJ","marks":16},{"name":"eA51fuu","marks":16},{"name":"eixqfa0O4c","marks":2},{"name":"FMMBgL5g3N","marks":94},{"name":"1jzp427iZe","marks":37},{"name":"2NFh6ZlNX","marks":34},{"name":"kie0Zk6NH","marks":36},{"name":"u4O","marks":90},{"name":"WDZ","marks":44},{"name":"tUw9","marks":87},{"name":"P1r","marks":46},{"name":"uqRIH","marks":67},{"name":"Fy6TZdM8n","marks":63},{"name":"GE4iRCz","marks":7},{"name":"okh6XQjFtY","marks":95},{"name":"QuCYWTR","marks":37},{"name":"L4c","marks":10},{"name":"YVX17mj3Su","marks":42},{"name":"Nm","marks":53},{"name":"T677pE","marks":60},{"name":"JQZB","marks":58},{"name":"hjd","marks":40},{"name":"Nu","marks":50},{"name":"TwyhMm2","marks":22},{"name":"Y6f","marks":51},{"name":"QGKL","marks":28},{"name":"P6U","marks":22},{"name":"5","marks":87},{"name":"oF2wV1","marks":50},{"name":"g","marks":20},{"name":"PVsbIMnyE","marks":76},{"name":"CLR","marks":27},{"name":"5qN8Bz","marks":92},{"name":"XtPBwNNa","marks":15},{"name":"h2pLDy","marks":47},{"name":"un0mT","marks":58},{"name":"S","marks":21},{"name":"kTlZpMwnl","marks":34},{"name":"hyK8GXcbN1","marks":46},{"name":"N","marks":88},{"name":"JKvSp4","marks":96},{"name":"80Z","marks":29},{"name":"0zZpGMPbo","marks":33},{"name":"PEL","marks":8},{"name":"SNjmAp","marks":64},{"name":"DKTiN8UX","marks":52},{"name":"Kte0T","marks":9},{"name":"EHUgqLn","marks":29},{"name":"eZcT","marks":55},{"name":"WGmDnZ1OlN","marks":27},{"name":"5H","marks":75},{"name":"HB","marks":39},{"name":"VnGv","marks":79},{"name":"EY6KZAW4T","marks":96},{"name":"nTe","marks":11},{"name":"4KsC","marks":30},{"name":"LpAS","marks":57},{"name":"bQnu","marks":88},{"name":"GWMqfuXo","marks":96},{"name":"D5jg5","marks":11},{"name":"TN","marks":11},{"name":"rL","marks":41},{"name":"unF","marks":13},{"name":"O2Ps","marks":48},{"name":"VoyYBzAFTU","marks":54},{"name":"fJgOIRMzuG","marks":57},{"name":"r7691Rn8Zg","marks":2},{"name":"ijKu4juCpC","marks":87},{"name":"nrD2","marks":94}]